testuploadhh/__init__.py
testuploadhh/cos/__init__.py
testuploadhh/cos/hh_cos.py
testuploadhh/sin/__init__.py
testuploadhh/sin/hh_sin.py
testuploadhh-3.0.1.dist-info/LICENSE.txt
testuploadhh-3.0.1.dist-info/METADATA
testuploadhh-3.0.1.dist-info/WHEEL
testuploadhh-3.0.1.dist-info/top_level.txt
testuploadhh-3.0.1.dist-info/RECORD
