Metadata-Version: 2.1
Name: testuploadhh
Version: 3.0.1
Summary: testforpypi pkg to training my own package to upload to TestPypi
Home-page: https://hh.com
Author: Huang Hao
Author-email: ironlionwg@outlook.com
Classifier: Programming Language :: Python :: 3
Classifier: License :: OSI Approved :: MIT License
Classifier: Operating System :: OS Independent
Requires-Python: >=3.6
License-File: LICENSE.txt
